[
    {
        "name": "司马炎",
        "era_name": "泰始／咸宁／太康／太熙",
        "temple_name": "世祖",
        "life_span_start_time": "236-01-01",
        "life_span_end_time": "290-05-16",
        "reign_start_time": "266-02-08",
        "reign_end_time": "290-05-16",
        "relatedPolities": "西晋"
    },
    {
        "name": "司马衷",
        "era_name": "永熙／永平／元康／永康／永宁／太安／永安／建武／永兴／光熙",
        "temple_name": "",
        "life_span_start_time": "259-02-13",
        "life_span_end_time": "307-01-08",
        "reign_start_time": "290-05-17",
        "reign_end_time": "307-01-08",
        "relatedPolities": "西晋"
    },
    {
        "name": "司马炽",
        "era_name": "永嘉",
        "temple_name": "",
        "life_span_start_time": "284-01-01",
        "life_span_end_time": "313-01-01",
        "reign_start_time": "307-01-08",
        "reign_end_time": "313-01-01",
        "relatedPolities": "西晋"
    },
    {
        "name": "司马邺",
        "era_name": "建兴",
        "temple_name": "",
        "life_span_start_time": "300-01-01",
        "life_span_end_time": "318-02-07",
        "reign_start_time": "313-06-07",
        "reign_end_time": "316-01-01",
        "relatedPolities": "西晋"
    }
]
